Janex/Janex.py
Janex/JanexCode.py
Janex/__init__.py
Janex/chat.py
Janex/main.py
Janex/JanexSub/JanexSub.py
Janex/JanexSub/__init__.py
Janex-0.0.11.dist-info/LICENSE
Janex-0.0.11.dist-info/METADATA
Janex-0.0.11.dist-info/WHEEL
Janex-0.0.11.dist-info/top_level.txt
Janex-0.0.11.dist-info/RECORD
